{"slug":"all_campaigns_anoneditwarning","format":"csv","type":"timeseries","url":"https://datasets.wikimedia.org/public-datasets/all/registrations/campaigns_anon.csv","name":"[all] New account registrations (anonymous edit warning campaign)","shortName":"all_campaigns_anoneditwarning","desc":"","notes":"","columns":[{"id":"date","label":"date","type":"Date","index":0,"metricDefs":[]},{"id":"de","label":"de","type":"Number","index":1,"metricDefs":[]},{"id":"en","label":"en","type":"Number","index":2,"metricDefs":[]},{"id":"es","label":"es","type":"Number","index":3,"metricDefs":[]},{"id":"fr","label":"fr","type":"Number","index":4,"metricDefs":[]},{"id":"it","label":"it","type":"Number","index":5,"metricDefs":[]},{"id":"ja","label":"ja","type":"Number","index":6,"metricDefs":[]},{"id":"pl","label":"pl","type":"Number","index":7,"metricDefs":[]},{"id":"pt","label":"pt","type":"Number","index":8,"metricDefs":[]},{"id":"ru","label":"ru","type":"Number","index":9,"metricDefs":[]},{"id":"zh","label":"zh","type":"Number","index":10,"metricDefs":[]}],"id":"all_campaigns_anoneditwarning"}