{
    "slug": "nlwiki_daily_reg",
    "format": "csv",
    "type": "timeseries",
    "url": "http://datasets.wikimedia.org/public-datasets/nlwiki/registrations/reg_daily.csv",
    "name": "[nlwiki] New account registrations",
    "shortName": "nlwiki_daily_reg",
    "desc": "",
    "notes": "",
    "columns": [
        {
            "id": "date",
            "label": "date",
            "type": "Date",
            "index": 0,
            "metricDefs": []
        },
        {
            "id": "new_accounts",
            "label": "new accounts",
            "type": "Number",
            "index": 1,
            "metricDefs": []
        }
    ],
    "id": "nlwiki_daily_reg"
}
